{
  "dStrings": [
    "Lilypad",
    "Cherrybomb",
    "Jalapeno",
    "Snowpea",
    "Wallnut",
    "Sunflower"
  ],
  "dtimer": [
    0,
    0,
    0,
    0,
    0,
    0
  ],
  "dcooldown": [
    false,
    false,
    false,
    false,
    false,
    false
  ],
  "jumlahdeck": 6,
  "s_sun": 50,
  "s_ticktime": 5,
  "s_tickspawn": 5,
  "bname": [],
  "bx": [],
  "by": [],
  "bdamage": [],
  "pname": [],
  "px": [],
  "py": [],
  "phealth": [],
  "ptimer": [],
  "pfp": [],
  "lptimer": [],
  "lpdamage": [],
  "zname": [],
  "zx": [],
  "zy": [],
  "zhealth": [],
  "ztimer": [],
  "zmoving": [],
  "zslowed": [],
  "zslowtime": [],
  "rzsun": [],
  "rztime": [],
  "aztime": [],
  "zjump": []
}